{
  "type": "Feature",
  "properties": {
    "name": "浙江农林大学",
    "description": "位于浙江省杭州市的一所高等学府"
  },
  "geometry": {
    "type": "Point",
    "coordinates": [
      119.7043,
      30.2685
    ]
  }
}